delos_lucia/__init__.py
delos_lucia/agents/chitchat.py
delos_lucia/clients/__init__.py
delos_lucia/clients/llm_client.py
delos_lucia/clients/openai_client.py
delos_lucia/config.py
delos_lucia/embeddings/embedding_client.py
delos_lucia/embeddings/openai_embedding_client.py
delos_lucia/extractors/extractor.py
delos_lucia/extractors/models.py
delos_lucia/extractors/noop_extractor.py
delos_lucia/extractors/openai_extractors.py
delos_lucia/pipeline_factory.py
delos_lucia/pipelines/__init__.py
delos_lucia/pipelines/knowledge_pipeline.py
delos_lucia/pipelines/search_pipeline.py
delos_lucia/prompts.py
delos_lucia/stores/__init__.py
delos_lucia/stores/info_store.py
delos_lucia/stores/info_store_clickhouse.py
delos_lucia/stores/info_store_neo4j.py
delos_lucia/te.py
delos_lucia/vectorstores/__init__.py
delos_lucia/vectorstores/milvus_vector_store.py
delos_lucia/vectorstores/vector_store.py
delos_lucia-0.1.1.dist-info/METADATA
delos_lucia-0.1.1.dist-info/WHEEL
delos_lucia-0.1.1.dist-info/RECORD
