Metadata-Version: 2.3
Name: delos-lucia
Version: 0.1.1
Summary: A modular Python library for personal AI Agent. Information extraction, keyword extraction, embeddings generation (via OpenAI), and storage in graph (Neo4j) and vector (Milvus) databases, with support for Redis caching and pluggable components.
License: Apache-2.0
Keywords: ai,llm,nlp,information extraction,keyword extraction,embedding,vector database,graph database,neo4j,milvus,openai,pipeline,agent
Author: sungminna
Author-email: sungmin.na330@gmail.com
Requires-Python: >=3.13,<4.0
Classifier: Development Status :: 3 - Alpha
Classifier: Intended Audience :: Developers
Classifier: License :: OSI Approved :: Apache Software License
Classifier: Operating System :: OS Independent
Classifier: Programming Language :: Python :: 3
Classifier: Programming Language :: Python :: 3.13
Classifier: Topic :: Scientific/Engineering :: Artificial Intelligence
Classifier: Topic :: Software Development :: Libraries :: Python Modules
Requires-Dist: clickhouse-connect (>=0.8.17,<0.9.0)
Requires-Dist: neo4j (>=5.28.1,<6.0.0)
Requires-Dist: openai (>=1.77.0,<2.0.0)
Requires-Dist: openai-agents (>=0.0.14,<0.0.15)
Requires-Dist: pydantic (>=2.11.4,<3.0.0)
Requires-Dist: pydantic-settings (>=2.9.1,<3.0.0)
Requires-Dist: pymilvus (>=2.5.8,<3.0.0)
Requires-Dist: python-dotenv (>=1.1.0,<2.0.0)
Requires-Dist: redis (>=6.0.0,<7.0.0)
Project-URL: Homepage, https://my.surfit.io/w/528136765
Project-URL: Repository, https://github.com/sungminna/mcp_poc/tree/main/lucia
